{"selectedVerses":[{"reference":{"book":"Deuteronomy","chapter":24,"verse":19},"text":"\u0022When you reap your harvest in your field and forget a sheaf in the field, you shall not go back to get it. It shall be for the sojourner, the fatherless, and the widow, that the LORD your God may bless you in all the work of your hands."},{"reference":{"book":"Psalms","chapter":16,"verse":7},"text":"I bless the LORD who gives me counsel; in the night also my heart instructs me."},{"reference":{"book":"Jeremiah","chapter":31,"verse":23},"text":"Thus says the LORD of hosts, the God of Israel: \u0022Once more they shall use these words in the land of Judah and in its cities, when I restore their fortunes: \u0022\u0027The LORD bless you, O habitation of righteousness, O holy hill!\u0027"},{"reference":{"book":"2 Samuel","chapter":6,"verse":20},"text":"And David returned to bless his household. But Michal the daughter of Saul came out to meet David and said, \u0022How the king of Israel honored himself today, uncovering himself today before the eyes of his servants\u0027 female servants, as one of the vulgar fellows shamelessly uncovers himself!\u0022"},{"reference":{"book":"Genesis","chapter":27,"verse":31},"text":"He also prepared delicious food and brought it to his father. And he said to his father, \u0022Let my father arise and eat of his son\u0027s game, that you may bless me.\u0022"}],"allVerseReferences":[{"book":"Genesis","chapter":12,"verse":2},{"book":"Genesis","chapter":12,"verse":3},{"book":"Genesis","chapter":17,"verse":16},{"book":"Genesis","chapter":22,"verse":17},{"book":"Genesis","chapter":26,"verse":24},{"book":"Genesis","chapter":27,"verse":7},{"book":"Genesis","chapter":26,"verse":3},{"book":"Genesis","chapter":27,"verse":10},{"book":"Genesis","chapter":27,"verse":38},{"book":"Genesis","chapter":27,"verse":25},{"book":"Genesis","chapter":27,"verse":4},{"book":"Genesis","chapter":27,"verse":31},{"book":"Genesis","chapter":27,"verse":19},{"book":"Genesis","chapter":27,"verse":34},{"book":"Genesis","chapter":28,"verse":3},{"book":"Genesis","chapter":32,"verse":26},{"book":"Genesis","chapter":48,"verse":9},{"book":"Genesis","chapter":48,"verse":16},{"book":"Genesis","chapter":49,"verse":25},{"book":"Exodus","chapter":12,"verse":32},{"book":"Exodus","chapter":20,"verse":24},{"book":"Exodus","chapter":23,"verse":25},{"book":"Numbers","chapter":22,"verse":6},{"book":"Numbers","chapter":6,"verse":23},{"book":"Numbers","chapter":6,"verse":24},{"book":"Numbers","chapter":6,"verse":27},{"book":"Numbers","chapter":24,"verse":1},{"book":"Numbers","chapter":24,"verse":9},{"book":"Numbers","chapter":23,"verse":11},{"book":"Numbers","chapter":23,"verse":20},{"book":"Deuteronomy","chapter":1,"verse":11},{"book":"Numbers","chapter":23,"verse":25},{"book":"Deuteronomy","chapter":7,"verse":13},{"book":"Deuteronomy","chapter":16,"verse":15},{"book":"Deuteronomy","chapter":10,"verse":8},{"book":"Deuteronomy","chapter":27,"verse":12},{"book":"Deuteronomy","chapter":24,"verse":13},{"book":"Deuteronomy","chapter":24,"verse":19},{"book":"Deuteronomy","chapter":30,"verse":16},{"book":"Deuteronomy","chapter":14,"verse":29},{"book":"Deuteronomy","chapter":8,"verse":10},{"book":"Deuteronomy","chapter":15,"verse":4},{"book":"Deuteronomy","chapter":15,"verse":6},{"book":"Deuteronomy","chapter":28,"verse":8},{"book":"Deuteronomy","chapter":15,"verse":10},{"book":"Deuteronomy","chapter":28,"verse":12},{"book":"Deuteronomy","chapter":15,"verse":18},{"book":"Deuteronomy","chapter":21,"verse":5},{"book":"Deuteronomy","chapter":23,"verse":20},{"book":"Deuteronomy","chapter":26,"verse":15},{"book":"Deuteronomy","chapter":33,"verse":11},{"book":"Joshua","chapter":8,"verse":33},{"book":"Judges","chapter":5,"verse":2},{"book":"Judges","chapter":5,"verse":9},{"book":"1 Samuel","chapter":2,"verse":20},{"book":"Ruth","chapter":2,"verse":4},{"book":"1 Samuel","chapter":9,"verse":13},{"book":"2 Samuel","chapter":6,"verse":20},{"book":"2 Samuel","chapter":7,"verse":29},{"book":"2 Samuel","chapter":8,"verse":10},{"book":"2 Samuel","chapter":21,"verse":3},{"book":"1 Chronicles","chapter":4,"verse":10},{"book":"1 Chronicles","chapter":16,"verse":43},{"book":"1 Chronicles","chapter":29,"verse":20},{"book":"1 Chronicles","chapter":17,"verse":27},{"book":"1 Chronicles","chapter":18,"verse":10},{"book":"Nehemiah","chapter":9,"verse":5},{"book":"Psalms","chapter":5,"verse":12},{"book":"Psalms","chapter":28,"verse":9},{"book":"Psalms","chapter":29,"verse":11},{"book":"Psalms","chapter":34,"verse":1},{"book":"Psalms","chapter":16,"verse":7},{"book":"Psalms","chapter":26,"verse":12},{"book":"Psalms","chapter":62,"verse":4},{"book":"Psalms","chapter":66,"verse":8},{"book":"Psalms","chapter":67,"verse":1},{"book":"Psalms","chapter":63,"verse":4},{"book":"Psalms","chapter":67,"verse":6},{"book":"Psalms","chapter":67,"verse":7},{"book":"Psalms","chapter":96,"verse":2},{"book":"Psalms","chapter":68,"verse":26},{"book":"Psalms","chapter":104,"verse":35},{"book":"Psalms","chapter":115,"verse":12},{"book":"Psalms","chapter":115,"verse":13},{"book":"Psalms","chapter":109,"verse":28},{"book":"Psalms","chapter":115,"verse":18},{"book":"Psalms","chapter":103,"verse":1},{"book":"Psalms","chapter":103,"verse":2},{"book":"Psalms","chapter":100,"verse":4},{"book":"Psalms","chapter":103,"verse":20},{"book":"Psalms","chapter":132,"verse":15},{"book":"Psalms","chapter":103,"verse":21},{"book":"Psalms","chapter":103,"verse":22},{"book":"Psalms","chapter":104,"verse":1},{"book":"Psalms","chapter":134,"verse":1},{"book":"Psalms","chapter":134,"verse":2},{"book":"Psalms","chapter":134,"verse":3},{"book":"Psalms","chapter":118,"verse":26},{"book":"Psalms","chapter":128,"verse":5},{"book":"Psalms","chapter":135,"verse":19},{"book":"Psalms","chapter":135,"verse":20},{"book":"Psalms","chapter":129,"verse":8},{"book":"Psalms","chapter":145,"verse":1},{"book":"Psalms","chapter":145,"verse":2},{"book":"Psalms","chapter":145,"verse":10},{"book":"Psalms","chapter":145,"verse":21},{"book":"Proverbs","chapter":30,"verse":11},{"book":"Isaiah","chapter":51,"verse":2},{"book":"Isaiah","chapter":65,"verse":16},{"book":"Jeremiah","chapter":4,"verse":2},{"book":"Jeremiah","chapter":31,"verse":23},{"book":"Haggai","chapter":2,"verse":19},{"book":"Luke","chapter":6,"verse":28},{"book":"Acts","chapter":3,"verse":26},{"book":"Romans","chapter":12,"verse":14},{"book":"1 Corinthians","chapter":4,"verse":12},{"book":"1 Corinthians","chapter":10,"verse":16},{"book":"James","chapter":3,"verse":9},{"book":"Hebrews","chapter":6,"verse":14},{"book":"1 Peter","chapter":3,"verse":9}]}