{"selectedVerses":[{"reference":{"book":"Matthew","chapter":27,"verse":6},"text":"But the chief priests, taking the pieces of silver, said, \u0022It is not lawful to put them into the treasury, since it is blood money.\u0022"},{"reference":{"book":"Ezra","chapter":8,"verse":29},"text":"Guard them and keep them until you weigh them before the chief priests and the Levites and the heads of fathers\u0027 houses in Israel at Jerusalem, within the chambers of the house of the LORD.\u0022"},{"reference":{"book":"John","chapter":18,"verse":35},"text":"Pilate answered, \u0022Am I a Jew? Your own nation and the chief priests have delivered you over to me. What have you done?\u0022"},{"reference":{"book":"1 Chronicles","chapter":12,"verse":18},"text":"Then the Spirit clothed Amasai, chief of the thirty, and he said, \u0022We are yours, O David, and with you, O son of Jesse! Peace, peace to you, and peace to your helpers! For your God helps you.\u0022Then David received them and made them officers of his troops."},{"reference":{"book":"Luke","chapter":22,"verse":4},"text":"He went away and conferred with the chief priests and officers how he might betray him to them."}],"allVerseReferences":[{"book":"Genesis","chapter":36,"verse":30},{"book":"Genesis","chapter":40,"verse":9},{"book":"Genesis","chapter":40,"verse":16},{"book":"Genesis","chapter":40,"verse":20},{"book":"Genesis","chapter":40,"verse":21},{"book":"Genesis","chapter":40,"verse":22},{"book":"Genesis","chapter":40,"verse":23},{"book":"Genesis","chapter":40,"verse":2},{"book":"Genesis","chapter":41,"verse":9},{"book":"Genesis","chapter":41,"verse":10},{"book":"Exodus","chapter":24,"verse":11},{"book":"Numbers","chapter":2,"verse":18},{"book":"Numbers","chapter":2,"verse":20},{"book":"Numbers","chapter":2,"verse":22},{"book":"Numbers","chapter":2,"verse":25},{"book":"Numbers","chapter":2,"verse":27},{"book":"Numbers","chapter":2,"verse":29},{"book":"Numbers","chapter":2,"verse":3},{"book":"Numbers","chapter":3,"verse":24},{"book":"Numbers","chapter":2,"verse":5},{"book":"Numbers","chapter":7,"verse":18},{"book":"Numbers","chapter":2,"verse":7},{"book":"Numbers","chapter":2,"verse":10},{"book":"Numbers","chapter":3,"verse":30},{"book":"Numbers","chapter":2,"verse":12},{"book":"Numbers","chapter":7,"verse":24},{"book":"Numbers","chapter":3,"verse":32},{"book":"Numbers","chapter":2,"verse":14},{"book":"Numbers","chapter":3,"verse":35},{"book":"Numbers","chapter":7,"verse":30},{"book":"Numbers","chapter":7,"verse":36},{"book":"Numbers","chapter":13,"verse":2},{"book":"Numbers","chapter":7,"verse":42},{"book":"Leviticus","chapter":21,"verse":10},{"book":"Numbers","chapter":7,"verse":48},{"book":"Numbers","chapter":7,"verse":54},{"book":"Numbers","chapter":7,"verse":60},{"book":"Numbers","chapter":7,"verse":66},{"book":"Numbers","chapter":7,"verse":72},{"book":"Numbers","chapter":7,"verse":78},{"book":"Numbers","chapter":7,"verse":11},{"book":"Numbers","chapter":17,"verse":6},{"book":"Numbers","chapter":34,"verse":18},{"book":"Numbers","chapter":34,"verse":22},{"book":"Numbers","chapter":34,"verse":23},{"book":"Numbers","chapter":34,"verse":24},{"book":"Numbers","chapter":34,"verse":25},{"book":"Numbers","chapter":34,"verse":26},{"book":"Numbers","chapter":34,"verse":27},{"book":"Numbers","chapter":34,"verse":28},{"book":"Numbers","chapter":25,"verse":14},{"book":"Numbers","chapter":25,"verse":18},{"book":"1 Samuel","chapter":21,"verse":7},{"book":"2 Samuel","chapter":23,"verse":18},{"book":"2 Samuel","chapter":23,"verse":8},{"book":"2 Samuel","chapter":23,"verse":13},{"book":"1 Kings","chapter":9,"verse":23},{"book":"1 Kings","chapter":5,"verse":16},{"book":"2 Kings","chapter":24,"verse":15},{"book":"2 Kings","chapter":25,"verse":18},{"book":"1 Chronicles","chapter":8,"verse":28},{"book":"1 Chronicles","chapter":7,"verse":3},{"book":"1 Chronicles","chapter":12,"verse":3},{"book":"1 Chronicles","chapter":5,"verse":2},{"book":"1 Chronicles","chapter":12,"verse":9},{"book":"1 Chronicles","chapter":9,"verse":11},{"book":"1 Chronicles","chapter":5,"verse":6},{"book":"1 Chronicles","chapter":5,"verse":7},{"book":"1 Chronicles","chapter":9,"verse":17},{"book":"1 Chronicles","chapter":15,"verse":5},{"book":"1 Chronicles","chapter":15,"verse":6},{"book":"1 Chronicles","chapter":5,"verse":12},{"book":"1 Chronicles","chapter":15,"verse":7},{"book":"1 Chronicles","chapter":15,"verse":8},{"book":"1 Chronicles","chapter":12,"verse":18},{"book":"1 Chronicles","chapter":15,"verse":9},{"book":"1 Chronicles","chapter":9,"verse":20},{"book":"1 Chronicles","chapter":15,"verse":10},{"book":"1 Chronicles","chapter":5,"verse":15},{"book":"1 Chronicles","chapter":24,"verse":21},{"book":"1 Chronicles","chapter":11,"verse":6},{"book":"1 Chronicles","chapter":24,"verse":23},{"book":"1 Chronicles","chapter":9,"verse":26},{"book":"1 Chronicles","chapter":11,"verse":11},{"book":"1 Chronicles","chapter":26,"verse":24},{"book":"1 Chronicles","chapter":11,"verse":15},{"book":"1 Chronicles","chapter":11,"verse":20},{"book":"1 Chronicles","chapter":26,"verse":31},{"book":"1 Chronicles","chapter":23,"verse":8},{"book":"1 Chronicles","chapter":23,"verse":11},{"book":"1 Chronicles","chapter":27,"verse":3},{"book":"1 Chronicles","chapter":27,"verse":5},{"book":"1 Chronicles","chapter":23,"verse":16},{"book":"1 Chronicles","chapter":16,"verse":5},{"book":"1 Chronicles","chapter":23,"verse":17},{"book":"1 Chronicles","chapter":23,"verse":18},{"book":"1 Chronicles","chapter":23,"verse":19},{"book":"1 Chronicles","chapter":23,"verse":20},{"book":"2 Chronicles","chapter":8,"verse":10},{"book":"1 Chronicles","chapter":27,"verse":16},{"book":"1 Chronicles","chapter":26,"verse":10},{"book":"1 Chronicles","chapter":24,"verse":4},{"book":"1 Chronicles","chapter":26,"verse":12},{"book":"2 Chronicles","chapter":11,"verse":22},{"book":"1 Chronicles","chapter":18,"verse":17},{"book":"2 Chronicles","chapter":24,"verse":6},{"book":"2 Chronicles","chapter":24,"verse":11},{"book":"2 Chronicles","chapter":26,"verse":20},{"book":"2 Chronicles","chapter":19,"verse":11},{"book":"2 Chronicles","chapter":31,"verse":10},{"book":"2 Chronicles","chapter":31,"verse":12},{"book":"2 Chronicles","chapter":31,"verse":13},{"book":"2 Chronicles","chapter":35,"verse":8},{"book":"Ezra","chapter":8,"verse":29},{"book":"Ezra","chapter":9,"verse":2},{"book":"Ezra","chapter":7,"verse":5},{"book":"Job","chapter":29,"verse":25},{"book":"Proverbs","chapter":6,"verse":7},{"book":"Song of Solomon","chapter":4,"verse":14},{"book":"Isaiah","chapter":20,"verse":1},{"book":"Jeremiah","chapter":20,"verse":1},{"book":"Jeremiah","chapter":31,"verse":7},{"book":"Jeremiah","chapter":39,"verse":13},{"book":"Ezekiel","chapter":17,"verse":13},{"book":"Jeremiah","chapter":41,"verse":1},{"book":"Jeremiah","chapter":52,"verse":24},{"book":"Ezekiel","chapter":38,"verse":2},{"book":"Ezekiel","chapter":38,"verse":3},{"book":"Ezekiel","chapter":39,"verse":1},{"book":"Daniel","chapter":4,"verse":9},{"book":"Daniel","chapter":2,"verse":48},{"book":"Daniel","chapter":1,"verse":3},{"book":"Daniel","chapter":1,"verse":7},{"book":"Daniel","chapter":1,"verse":8},{"book":"Daniel","chapter":1,"verse":9},{"book":"Daniel","chapter":1,"verse":10},{"book":"Daniel","chapter":1,"verse":11},{"book":"Daniel","chapter":5,"verse":11},{"book":"Daniel","chapter":1,"verse":18},{"book":"Daniel","chapter":10,"verse":13},{"book":"Matthew","chapter":2,"verse":4},{"book":"Matthew","chapter":20,"verse":18},{"book":"Matthew","chapter":16,"verse":21},{"book":"Matthew","chapter":21,"verse":45},{"book":"Matthew","chapter":26,"verse":3},{"book":"Matthew","chapter":21,"verse":15},{"book":"Matthew","chapter":26,"verse":14},{"book":"Matthew","chapter":21,"verse":23},{"book":"Matthew","chapter":27,"verse":1},{"book":"Matthew","chapter":27,"verse":3},{"book":"Matthew","chapter":27,"verse":62},{"book":"Matthew","chapter":27,"verse":6},{"book":"Matthew","chapter":27,"verse":12},{"book":"Matthew","chapter":27,"verse":20},{"book":"Matthew","chapter":28,"verse":11},{"book":"Matthew","chapter":27,"verse":41},{"book":"Matthew","chapter":26,"verse":47},{"book":"Mark","chapter":14,"verse":1},{"book":"Mark","chapter":8,"verse":31},{"book":"Matthew","chapter":26,"verse":59},{"book":"Mark","chapter":14,"verse":10},{"book":"Mark","chapter":15,"verse":1},{"book":"Mark","chapter":15,"verse":3},{"book":"Mark","chapter":15,"verse":10},{"book":"Mark","chapter":15,"verse":11},{"book":"Mark","chapter":11,"verse":18},{"book":"Mark","chapter":14,"verse":43},{"book":"Mark","chapter":10,"verse":33},{"book":"Mark","chapter":11,"verse":27},{"book":"Mark","chapter":14,"verse":53},{"book":"Mark","chapter":14,"verse":55},{"book":"Mark","chapter":15,"verse":31},{"book":"Luke","chapter":20,"verse":1},{"book":"Luke","chapter":9,"verse":22},{"book":"Luke","chapter":19,"verse":2},{"book":"Luke","chapter":22,"verse":52},{"book":"Luke","chapter":20,"verse":19},{"book":"Luke","chapter":22,"verse":2},{"book":"Luke","chapter":22,"verse":4},{"book":"Luke","chapter":22,"verse":66},{"book":"Luke","chapter":23,"verse":4},{"book":"Luke","chapter":23,"verse":10},{"book":"Luke","chapter":23,"verse":13},{"book":"Luke","chapter":19,"verse":47},{"book":"Luke","chapter":24,"verse":20},{"book":"John","chapter":7,"verse":32},{"book":"John","chapter":7,"verse":45},{"book":"John","chapter":11,"verse":47},{"book":"John","chapter":18,"verse":35},{"book":"John","chapter":11,"verse":57},{"book":"John","chapter":12,"verse":10},{"book":"John","chapter":19,"verse":6},{"book":"John","chapter":19,"verse":15},{"book":"John","chapter":19,"verse":21},{"book":"John","chapter":18,"verse":3},{"book":"Acts","chapter":5,"verse":24},{"book":"Acts","chapter":9,"verse":14},{"book":"Acts","chapter":4,"verse":23},{"book":"Acts","chapter":9,"verse":21},{"book":"Acts","chapter":14,"verse":12},{"book":"Acts","chapter":26,"verse":10},{"book":"Acts","chapter":26,"verse":12},{"book":"Acts","chapter":28,"verse":7},{"book":"Acts","chapter":22,"verse":30},{"book":"Acts","chapter":25,"verse":2},{"book":"Acts","chapter":25,"verse":15},{"book":"Acts","chapter":23,"verse":14},{"book":"1 Peter","chapter":5,"verse":4}]}