{"selectedVerses":[{"reference":{"book":"Revelation","chapter":1,"verse":5},"text":"and from Jesus Christ the faithful witness, the firstborn of the dead, and the ruler of kings on earth.To him who loves us and has freed us from our sins by his blood"},{"reference":{"book":"Acts","chapter":13,"verse":39},"text":"from which you could not be freed by the law of Moses."},{"reference":{"book":"Luke","chapter":13,"verse":12},"text":"When Jesus saw her, he called her over and said to her, \u0022Woman, you are freed from your disability.\u0022"},{"reference":{"book":"Psalms","chapter":81,"verse":6},"text":"\u0022I relieved your shoulder of the burden; your hands were freed from the basket."},{"reference":{"book":"2 Kings","chapter":25,"verse":27},"text":"And in the thirty-seventh year of the exile of Jehoiachin king of Judah, in the twelfth month, on the twenty-seventh day of the month, Evil-merodach king of Babylon, in the year that he began to reign, graciously freed Jehoiachin king of Judah from prison."}],"allVerseReferences":[{"book":"2 Kings","chapter":25,"verse":27},{"book":"Psalms","chapter":81,"verse":6},{"book":"Luke","chapter":13,"verse":12},{"book":"Acts","chapter":13,"verse":38},{"book":"Acts","chapter":13,"verse":39},{"book":"Revelation","chapter":1,"verse":5}]}