{"selectedVerses":[{"reference":{"book":"Acts","chapter":16,"verse":40},"text":"So they went out of the prison and visited Lydia. And when they had seen the brothers, they encouraged them and departed."},{"reference":{"book":"Acts","chapter":16,"verse":14},"text":"One who heard us was a woman named Lydia, from the city of Thyatira, a seller of purple goods, who was a worshiper of God. The Lord opened her heart to pay attention to what was said by Paul."}],"allVerseReferences":[{"book":"Acts","chapter":16,"verse":40},{"book":"Acts","chapter":16,"verse":14}]}