{"selectedVerses":[{"reference":{"book":"2 Timothy","chapter":4,"verse":21},"text":"Do your best to come before winter. Eubulus sends greetings to you, as do Pudens and Linus and Claudia and all the brothers."},{"reference":{"book":"Matthew","chapter":5,"verse":45},"text":"so that you may be sons of your Father who is in heaven. For he makes his sun rise on the evil and on the good, and sends rain on the just and on the unjust."},{"reference":{"book":"Psalms","chapter":147,"verse":18},"text":"He sends out his word, and melts them; he makes his wind blow and the waters flow."},{"reference":{"book":"Proverbs","chapter":26,"verse":6},"text":"Whoever sends a message by the hand of a fool cuts off his own feet and drinks violence."},{"reference":{"book":"2 Thessalonians","chapter":2,"verse":11},"text":"Therefore God sends them a strong delusion, so that they may believe what is false,"}],"allVerseReferences":[{"book":"Deuteronomy","chapter":24,"verse":1},{"book":"Deuteronomy","chapter":24,"verse":3},{"book":"1 Kings","chapter":17,"verse":14},{"book":"2 Kings","chapter":5,"verse":7},{"book":"Job","chapter":5,"verse":10},{"book":"Job","chapter":12,"verse":15},{"book":"Psalms","chapter":68,"verse":33},{"book":"Psalms","chapter":110,"verse":2},{"book":"Psalms","chapter":147,"verse":15},{"book":"Psalms","chapter":147,"verse":18},{"book":"Proverbs","chapter":26,"verse":6},{"book":"Isaiah","chapter":18,"verse":2},{"book":"Jeremiah","chapter":17,"verse":8},{"book":"Jeremiah","chapter":42,"verse":5},{"book":"Matthew","chapter":5,"verse":45},{"book":"Luke","chapter":14,"verse":32},{"book":"2 Thessalonians","chapter":2,"verse":11},{"book":"2 Timothy","chapter":4,"verse":21},{"book":"Philemon","chapter":1,"verse":23},{"book":"1 Peter","chapter":5,"verse":13}]}