{"selectedVerses":[{"reference":{"book":"Genesis","chapter":21,"verse":31},"text":"Therefore that place was called Beersheba, because there both of them swore an oath."},{"reference":{"book":"Deuteronomy","chapter":26,"verse":15},"text":"Look down from your holy habitation, from heaven, and bless your people Israel and the ground that you have given us, as you swore to our fathers, a land flowing with milk and honey.\u0027"},{"reference":{"book":"Deuteronomy","chapter":4,"verse":21},"text":"Furthermore, the LORD was angry with me because of you, and he swore that I should not cross the Jordan, and that I should not enter the good land that the LORD your God is giving you for an inheritance."},{"reference":{"book":"Deuteronomy","chapter":34,"verse":4},"text":"And the LORD said to him, \u0022This is the land of which I swore to Abraham, to Isaac, and to Jacob, \u0027I will give it to your offspring.\u0027 I have let you see it with your eyes, but you shall not go over there.\u0022"},{"reference":{"book":"Joshua","chapter":21,"verse":43},"text":"Thus the LORD gave to Israel all the land that he swore to give to their fathers. And they took possession of it, and they settled there."}],"allVerseReferences":[{"book":"Genesis","chapter":21,"verse":31},{"book":"Genesis","chapter":24,"verse":7},{"book":"Genesis","chapter":24,"verse":9},{"book":"Genesis","chapter":26,"verse":3},{"book":"Genesis","chapter":25,"verse":33},{"book":"Genesis","chapter":31,"verse":53},{"book":"Genesis","chapter":47,"verse":31},{"book":"Exodus","chapter":6,"verse":8},{"book":"Genesis","chapter":50,"verse":24},{"book":"Exodus","chapter":13,"verse":5},{"book":"Exodus","chapter":13,"verse":11},{"book":"Exodus","chapter":32,"verse":13},{"book":"Exodus","chapter":33,"verse":1},{"book":"Numbers","chapter":14,"verse":16},{"book":"Numbers","chapter":14,"verse":23},{"book":"Numbers","chapter":14,"verse":30},{"book":"Numbers","chapter":11,"verse":12},{"book":"Deuteronomy","chapter":1,"verse":8},{"book":"Numbers","chapter":32,"verse":10},{"book":"Numbers","chapter":32,"verse":11},{"book":"Deuteronomy","chapter":4,"verse":21},{"book":"Deuteronomy","chapter":6,"verse":10},{"book":"Deuteronomy","chapter":8,"verse":18},{"book":"Deuteronomy","chapter":4,"verse":31},{"book":"Deuteronomy","chapter":1,"verse":34},{"book":"Deuteronomy","chapter":9,"verse":5},{"book":"Deuteronomy","chapter":6,"verse":18},{"book":"Deuteronomy","chapter":1,"verse":35},{"book":"Deuteronomy","chapter":6,"verse":23},{"book":"Deuteronomy","chapter":11,"verse":9},{"book":"Deuteronomy","chapter":7,"verse":8},{"book":"Deuteronomy","chapter":13,"verse":17},{"book":"Deuteronomy","chapter":11,"verse":21},{"book":"Deuteronomy","chapter":7,"verse":12},{"book":"Deuteronomy","chapter":7,"verse":13},{"book":"Deuteronomy","chapter":10,"verse":11},{"book":"Deuteronomy","chapter":8,"verse":1},{"book":"Deuteronomy","chapter":30,"verse":20},{"book":"Deuteronomy","chapter":28,"verse":11},{"book":"Joshua","chapter":1,"verse":6},{"book":"Deuteronomy","chapter":26,"verse":3},{"book":"Deuteronomy","chapter":31,"verse":20},{"book":"Deuteronomy","chapter":29,"verse":13},{"book":"Deuteronomy","chapter":31,"verse":21},{"book":"Deuteronomy","chapter":31,"verse":23},{"book":"Deuteronomy","chapter":26,"verse":15},{"book":"Joshua","chapter":9,"verse":15},{"book":"Joshua","chapter":5,"verse":6},{"book":"Joshua","chapter":9,"verse":20},{"book":"Deuteronomy","chapter":34,"verse":4},{"book":"Joshua","chapter":14,"verse":9},{"book":"Joshua","chapter":6,"verse":22},{"book":"Joshua","chapter":21,"verse":43},{"book":"Judges","chapter":2,"verse":1},{"book":"1 Samuel","chapter":19,"verse":6},{"book":"1 Samuel","chapter":24,"verse":22},{"book":"2 Samuel","chapter":3,"verse":35},{"book":"1 Samuel","chapter":28,"verse":10},{"book":"1 Kings","chapter":1,"verse":17},{"book":"1 Kings","chapter":1,"verse":29},{"book":"1 Kings","chapter":1,"verse":30},{"book":"1 Kings","chapter":2,"verse":8},{"book":"2 Samuel","chapter":21,"verse":17},{"book":"1 Kings","chapter":2,"verse":23},{"book":"2 Kings","chapter":25,"verse":24},{"book":"2 Chronicles","chapter":15,"verse":14},{"book":"Psalms","chapter":95,"verse":11},{"book":"Psalms","chapter":89,"verse":49},{"book":"Psalms","chapter":106,"verse":26},{"book":"Psalms","chapter":132,"verse":11},{"book":"Psalms","chapter":132,"verse":2},{"book":"Isaiah","chapter":54,"verse":9},{"book":"Jeremiah","chapter":11,"verse":5},{"book":"Jeremiah","chapter":32,"verse":22},{"book":"Jeremiah","chapter":38,"verse":16},{"book":"Jeremiah","chapter":40,"verse":9},{"book":"Ezekiel","chapter":20,"verse":28},{"book":"Ezekiel","chapter":20,"verse":42},{"book":"Ezekiel","chapter":47,"verse":14},{"book":"Daniel","chapter":12,"verse":7},{"book":"Luke","chapter":1,"verse":73},{"book":"Hebrews","chapter":3,"verse":11},{"book":"Hebrews","chapter":4,"verse":3},{"book":"Hebrews","chapter":6,"verse":13},{"book":"Revelation","chapter":10,"verse":6},{"book":"Ezekiel","chapter":20,"verse":5},{"book":"Ezekiel","chapter":20,"verse":6},{"book":"Ezekiel","chapter":20,"verse":15},{"book":"Ezekiel","chapter":20,"verse":23}]}