{"selectedVerses":[{"reference":{"book":"Numbers","chapter":7,"verse":3},"text":"and brought their offerings before the LORD, six wagons and twelve oxen, a wagon for every two of the chiefs, and for each one an ox. They brought them before the tabernacle."},{"reference":{"book":"Psalms","chapter":65,"verse":11},"text":"You crown the year with your bounty; your wagon tracks overflow with abundance."}],"allVerseReferences":[{"book":"Numbers","chapter":7,"verse":3},{"book":"Psalms","chapter":65,"verse":11}]}