{"selectedVerses":[{"reference":{"book":"Jeremiah","chapter":9,"verse":21},"text":"For death has come up into our windows; it has entered our palaces, cutting off the children from the streets and the young men from the squares."},{"reference":{"book":"2 Samuel","chapter":1,"verse":15},"text":"Then David called one of the young men and said, \u0022Go, execute him.\u0022 And he struck him down so that he died."},{"reference":{"book":"Ruth","chapter":2,"verse":22},"text":"And Naomi said to Ruth, her daughter-in-law, \u0022It is good, my daughter, that you go out with his young women, lest in another field you be assaulted.\u0022"},{"reference":{"book":"2 Samuel","chapter":18,"verse":32},"text":"The king said to the Cushite, \u0022Is it well with the young man Absalom?\u0022 And the Cushite answered, \u0022May the enemies of my lord the king and all who rise up against you for evil be like that young man.\u0022"},{"reference":{"book":"Isaiah","chapter":62,"verse":5},"text":"For as a young man marries a young woman, so shall your sons marry you, and as the bridegroom rejoices over the bride, so shall your God rejoice over you."}],"allVerseReferences":[{"book":"Genesis","chapter":4,"verse":23},{"book":"Genesis","chapter":15,"verse":9},{"book":"Genesis","chapter":14,"verse":24},{"book":"Genesis","chapter":19,"verse":4},{"book":"Genesis","chapter":18,"verse":7},{"book":"Genesis","chapter":22,"verse":3},{"book":"Genesis","chapter":22,"verse":19},{"book":"Genesis","chapter":22,"verse":5},{"book":"Genesis","chapter":24,"verse":55},{"book":"Genesis","chapter":24,"verse":28},{"book":"Genesis","chapter":24,"verse":57},{"book":"Genesis","chapter":27,"verse":9},{"book":"Genesis","chapter":24,"verse":14},{"book":"Genesis","chapter":24,"verse":16},{"book":"Genesis","chapter":24,"verse":61},{"book":"Genesis","chapter":27,"verse":16},{"book":"Genesis","chapter":34,"verse":12},{"book":"Genesis","chapter":34,"verse":3},{"book":"Genesis","chapter":34,"verse":19},{"book":"Genesis","chapter":44,"verse":20},{"book":"Genesis","chapter":38,"verse":17},{"book":"Genesis","chapter":38,"verse":20},{"book":"Genesis","chapter":41,"verse":12},{"book":"Genesis","chapter":38,"verse":23},{"book":"Exodus","chapter":10,"verse":9},{"book":"Exodus","chapter":2,"verse":5},{"book":"Exodus","chapter":24,"verse":5},{"book":"Exodus","chapter":23,"verse":19},{"book":"Exodus","chapter":34,"verse":26},{"book":"Exodus","chapter":33,"verse":11},{"book":"Leviticus","chapter":22,"verse":28},{"book":"Numbers","chapter":15,"verse":11},{"book":"Numbers","chapter":11,"verse":27},{"book":"Numbers","chapter":31,"verse":18},{"book":"Deuteronomy","chapter":7,"verse":13},{"book":"Deuteronomy","chapter":22,"verse":6},{"book":"Deuteronomy","chapter":22,"verse":7},{"book":"Deuteronomy","chapter":14,"verse":21},{"book":"Deuteronomy","chapter":22,"verse":15},{"book":"Deuteronomy","chapter":22,"verse":16},{"book":"Deuteronomy","chapter":22,"verse":19},{"book":"Deuteronomy","chapter":22,"verse":20},{"book":"Deuteronomy","chapter":22,"verse":21},{"book":"Deuteronomy","chapter":22,"verse":24},{"book":"Deuteronomy","chapter":22,"verse":25},{"book":"Deuteronomy","chapter":28,"verse":50},{"book":"Deuteronomy","chapter":22,"verse":26},{"book":"Deuteronomy","chapter":28,"verse":51},{"book":"Deuteronomy","chapter":22,"verse":27},{"book":"Deuteronomy","chapter":28,"verse":4},{"book":"Deuteronomy","chapter":22,"verse":29},{"book":"Deuteronomy","chapter":28,"verse":18},{"book":"Deuteronomy","chapter":32,"verse":11},{"book":"Deuteronomy","chapter":32,"verse":25},{"book":"Joshua","chapter":6,"verse":21},{"book":"Joshua","chapter":6,"verse":23},{"book":"Judges","chapter":18,"verse":15},{"book":"Judges","chapter":13,"verse":15},{"book":"Judges","chapter":13,"verse":19},{"book":"Judges","chapter":13,"verse":24},{"book":"Judges","chapter":14,"verse":5},{"book":"Judges","chapter":6,"verse":19},{"book":"Judges","chapter":14,"verse":6},{"book":"Judges","chapter":19,"verse":13},{"book":"Judges","chapter":14,"verse":10},{"book":"1 Samuel","chapter":2,"verse":21},{"book":"Judges","chapter":9,"verse":54},{"book":"Judges","chapter":19,"verse":19},{"book":"Judges","chapter":16,"verse":26},{"book":"Ruth","chapter":4,"verse":12},{"book":"Judges","chapter":8,"verse":14},{"book":"1 Samuel","chapter":2,"verse":26},{"book":"1 Samuel","chapter":5,"verse":9},{"book":"Judges","chapter":8,"verse":20},{"book":"1 Samuel","chapter":9,"verse":2},{"book":"Judges","chapter":15,"verse":1},{"book":"1 Samuel","chapter":9,"verse":3},{"book":"Ruth","chapter":2,"verse":5},{"book":"Judges","chapter":21,"verse":12},{"book":"Ruth","chapter":2,"verse":6},{"book":"Ruth","chapter":2,"verse":8},{"book":"Ruth","chapter":2,"verse":9},{"book":"Judges","chapter":17,"verse":7},{"book":"1 Samuel","chapter":3,"verse":1},{"book":"1 Samuel","chapter":9,"verse":11},{"book":"Judges","chapter":17,"verse":11},{"book":"Judges","chapter":17,"verse":12},{"book":"Ruth","chapter":2,"verse":15},{"book":"1 Samuel","chapter":3,"verse":8},{"book":"Judges","chapter":18,"verse":3},{"book":"Ruth","chapter":2,"verse":21},{"book":"1 Samuel","chapter":1,"verse":24},{"book":"Ruth","chapter":2,"verse":22},{"book":"1 Samuel","chapter":9,"verse":22},{"book":"Ruth","chapter":2,"verse":23},{"book":"Ruth","chapter":3,"verse":2},{"book":"1 Samuel","chapter":21,"verse":2},{"book":"1 Samuel","chapter":21,"verse":4},{"book":"1 Samuel","chapter":10,"verse":3},{"book":"Ruth","chapter":3,"verse":10},{"book":"1 Samuel","chapter":21,"verse":5},{"book":"1 Samuel","chapter":2,"verse":17},{"book":"1 Samuel","chapter":16,"verse":18},{"book":"1 Samuel","chapter":16,"verse":20},{"book":"1 Samuel","chapter":25,"verse":42},{"book":"1 Samuel","chapter":17,"verse":58},{"book":"1 Samuel","chapter":8,"verse":16},{"book":"2 Samuel","chapter":1,"verse":6},{"book":"1 Samuel","chapter":20,"verse":21},{"book":"2 Samuel","chapter":1,"verse":13},{"book":"2 Samuel","chapter":1,"verse":15},{"book":"1 Samuel","chapter":14,"verse":1},{"book":"1 Samuel","chapter":25,"verse":5},{"book":"1 Samuel","chapter":26,"verse":22},{"book":"1 Samuel","chapter":25,"verse":8},{"book":"1 Samuel","chapter":14,"verse":6},{"book":"1 Samuel","chapter":25,"verse":9},{"book":"1 Samuel","chapter":25,"verse":12},{"book":"2 Samuel","chapter":13,"verse":32},{"book":"1 Samuel","chapter":30,"verse":13},{"book":"1 Samuel","chapter":25,"verse":14},{"book":"2 Samuel","chapter":13,"verse":34},{"book":"1 Samuel","chapter":30,"verse":17},{"book":"1 Samuel","chapter":25,"verse":19},{"book":"2 Samuel","chapter":2,"verse":14},{"book":"1 Samuel","chapter":25,"verse":25},{"book":"2 Samuel","chapter":2,"verse":21},{"book":"1 Samuel","chapter":25,"verse":27},{"book":"2 Samuel","chapter":4,"verse":12},{"book":"2 Samuel","chapter":9,"verse":12},{"book":"2 Samuel","chapter":16,"verse":2},{"book":"2 Samuel","chapter":18,"verse":5},{"book":"2 Samuel","chapter":14,"verse":21},{"book":"2 Samuel","chapter":18,"verse":12},{"book":"2 Samuel","chapter":18,"verse":15},{"book":"2 Samuel","chapter":1,"verse":5},{"book":"2 Samuel","chapter":18,"verse":29},{"book":"2 Samuel","chapter":18,"verse":32},{"book":"2 Samuel","chapter":13,"verse":17},{"book":"2 Samuel","chapter":20,"verse":11},{"book":"2 Samuel","chapter":17,"verse":18},{"book":"1 Kings","chapter":1,"verse":2},{"book":"1 Kings","chapter":1,"verse":3},{"book":"1 Kings","chapter":1,"verse":4},{"book":"1 Kings","chapter":11,"verse":28},{"book":"1 Kings","chapter":12,"verse":8},{"book":"1 Kings","chapter":12,"verse":10},{"book":"1 Kings","chapter":12,"verse":14},{"book":"2 Kings","chapter":9,"verse":4},{"book":"2 Kings","chapter":9,"verse":6},{"book":"2 Kings","chapter":5,"verse":22},{"book":"2 Kings","chapter":8,"verse":12},{"book":"2 Kings","chapter":6,"verse":17},{"book":"1 Chronicles","chapter":12,"verse":28},{"book":"1 Chronicles","chapter":29,"verse":1},{"book":"2 Chronicles","chapter":15,"verse":13},{"book":"1 Chronicles","chapter":22,"verse":5},{"book":"2 Chronicles","chapter":31,"verse":15},{"book":"2 Chronicles","chapter":13,"verse":7},{"book":"2 Chronicles","chapter":13,"verse":9},{"book":"2 Chronicles","chapter":10,"verse":8},{"book":"2 Chronicles","chapter":10,"verse":10},{"book":"2 Chronicles","chapter":10,"verse":14},{"book":"2 Chronicles","chapter":36,"verse":17},{"book":"2 Chronicles","chapter":35,"verse":7},{"book":"2 Chronicles","chapter":35,"verse":9},{"book":"Esther","chapter":4,"verse":4},{"book":"Esther","chapter":4,"verse":16},{"book":"Esther","chapter":2,"verse":2},{"book":"Esther","chapter":2,"verse":3},{"book":"Esther","chapter":2,"verse":4},{"book":"Esther","chapter":2,"verse":7},{"book":"Esther","chapter":2,"verse":8},{"book":"Esther","chapter":2,"verse":9},{"book":"Esther","chapter":6,"verse":3},{"book":"Esther","chapter":2,"verse":12},{"book":"Esther","chapter":2,"verse":13},{"book":"Esther","chapter":6,"verse":5},{"book":"Job","chapter":4,"verse":10},{"book":"Esther","chapter":3,"verse":13},{"book":"Job","chapter":19,"verse":18},{"book":"Job","chapter":14,"verse":9},{"book":"Job","chapter":29,"verse":8},{"book":"Job","chapter":1,"verse":19},{"book":"Job","chapter":39,"verse":30},{"book":"Job","chapter":32,"verse":6},{"book":"Psalms","chapter":17,"verse":12},{"book":"Job","chapter":38,"verse":39},{"book":"Job","chapter":38,"verse":41},{"book":"Job","chapter":39,"verse":3},{"book":"Job","chapter":39,"verse":4},{"book":"Job","chapter":39,"verse":16},{"book":"Psalms","chapter":29,"verse":6},{"book":"Psalms","chapter":34,"verse":10},{"book":"Psalms","chapter":37,"verse":25},{"book":"Psalms","chapter":58,"verse":6},{"book":"Psalms","chapter":78,"verse":31},{"book":"Psalms","chapter":84,"verse":3},{"book":"Psalms","chapter":91,"verse":13},{"book":"Psalms","chapter":78,"verse":63},{"book":"Psalms","chapter":104,"verse":21},{"book":"Psalms","chapter":119,"verse":9},{"book":"Psalms","chapter":105,"verse":34},{"book":"Psalms","chapter":147,"verse":9},{"book":"Psalms","chapter":148,"verse":12},{"book":"Psalms","chapter":144,"verse":14},{"book":"Proverbs","chapter":9,"verse":3},{"book":"Proverbs","chapter":7,"verse":7},{"book":"Proverbs","chapter":20,"verse":29},{"book":"Song of Solomon","chapter":2,"verse":17},{"book":"Song of Solomon","chapter":4,"verse":2},{"book":"Ecclesiastes","chapter":11,"verse":9},{"book":"Song of Solomon","chapter":8,"verse":14},{"book":"Isaiah","chapter":11,"verse":6},{"book":"Isaiah","chapter":11,"verse":7},{"book":"Isaiah","chapter":5,"verse":29},{"book":"Song of Solomon","chapter":6,"verse":6},{"book":"Song of Solomon","chapter":1,"verse":8},{"book":"Song of Solomon","chapter":6,"verse":9},{"book":"Song of Solomon","chapter":2,"verse":2},{"book":"Song of Solomon","chapter":2,"verse":3},{"book":"Isaiah","chapter":23,"verse":4},{"book":"Isaiah","chapter":9,"verse":17},{"book":"Song of Solomon","chapter":2,"verse":9},{"book":"Isaiah","chapter":20,"verse":4},{"book":"Isaiah","chapter":13,"verse":18},{"book":"Isaiah","chapter":7,"verse":21},{"book":"Isaiah","chapter":37,"verse":6},{"book":"Isaiah","chapter":34,"verse":7},{"book":"Isaiah","chapter":34,"verse":15},{"book":"Isaiah","chapter":31,"verse":4},{"book":"Isaiah","chapter":31,"verse":8},{"book":"Isaiah","chapter":40,"verse":11},{"book":"Isaiah","chapter":62,"verse":5},{"book":"Isaiah","chapter":65,"verse":20},{"book":"Isaiah","chapter":40,"verse":30},{"book":"Jeremiah","chapter":2,"verse":23},{"book":"Jeremiah","chapter":6,"verse":11},{"book":"Isaiah","chapter":53,"verse":2},{"book":"Isaiah","chapter":60,"verse":6},{"book":"Jeremiah","chapter":11,"verse":22},{"book":"Jeremiah","chapter":9,"verse":21},{"book":"Jeremiah","chapter":15,"verse":8},{"book":"Jeremiah","chapter":31,"verse":12},{"book":"Jeremiah","chapter":31,"verse":13},{"book":"Jeremiah","chapter":50,"verse":30},{"book":"Lamentations","chapter":2,"verse":10},{"book":"Lamentations","chapter":2,"verse":21},{"book":"Lamentations","chapter":4,"verse":3},{"book":"Jeremiah","chapter":51,"verse":3},{"book":"Ezekiel","chapter":9,"verse":6},{"book":"Ezekiel","chapter":17,"verse":4},{"book":"Lamentations","chapter":5,"verse":11},{"book":"Jeremiah","chapter":49,"verse":26},{"book":"Lamentations","chapter":5,"verse":13},{"book":"Lamentations","chapter":5,"verse":14},{"book":"Jeremiah","chapter":51,"verse":22},{"book":"Ezekiel","chapter":31,"verse":6},{"book":"Ezekiel","chapter":23,"verse":6},{"book":"Ezekiel","chapter":23,"verse":12},{"book":"Ezekiel","chapter":17,"verse":22},{"book":"Jeremiah","chapter":48,"verse":15},{"book":"Ezekiel","chapter":19,"verse":2},{"book":"Ezekiel","chapter":19,"verse":3},{"book":"Ezekiel","chapter":19,"verse":5},{"book":"Ezekiel","chapter":23,"verse":21},{"book":"Ezekiel","chapter":23,"verse":23},{"book":"Ezekiel","chapter":45,"verse":22},{"book":"Ezekiel","chapter":45,"verse":23},{"book":"Ezekiel","chapter":46,"verse":11},{"book":"Hosea","chapter":5,"verse":14},{"book":"Hosea","chapter":9,"verse":13},{"book":"Joel","chapter":2,"verse":28},{"book":"Amos","chapter":4,"verse":10},{"book":"Amos","chapter":8,"verse":13},{"book":"Amos","chapter":2,"verse":11},{"book":"Amos","chapter":3,"verse":4},{"book":"Nahum","chapter":2,"verse":11},{"book":"Nahum","chapter":2,"verse":13},{"book":"Micah","chapter":5,"verse":8},{"book":"Micah","chapter":2,"verse":9},{"book":"Zechariah","chapter":11,"verse":16},{"book":"Zechariah","chapter":9,"verse":17},{"book":"Zechariah","chapter":2,"verse":4},{"book":"Matthew","chapter":19,"verse":20},{"book":"Matthew","chapter":19,"verse":22},{"book":"Mark","chapter":14,"verse":51},{"book":"Luke","chapter":7,"verse":14},{"book":"Luke","chapter":2,"verse":24},{"book":"Mark","chapter":16,"verse":5},{"book":"Luke","chapter":15,"verse":29},{"book":"John","chapter":12,"verse":14},{"book":"Acts","chapter":5,"verse":6},{"book":"Acts","chapter":5,"verse":10},{"book":"John","chapter":21,"verse":18},{"book":"Acts","chapter":2,"verse":17},{"book":"Acts","chapter":7,"verse":58},{"book":"Acts","chapter":20,"verse":9},{"book":"Acts","chapter":23,"verse":17},{"book":"Acts","chapter":23,"verse":18},{"book":"Acts","chapter":23,"verse":22},{"book":"Titus","chapter":2,"verse":4},{"book":"Lamentations","chapter":1,"verse":15},{"book":"1 John","chapter":2,"verse":13},{"book":"1 John","chapter":2,"verse":14},{"book":"Lamentations","chapter":1,"verse":18},{"book":"Ezekiel","chapter":19,"verse":6},{"book":"Ezekiel","chapter":41,"verse":19},{"book":"Ezekiel","chapter":30,"verse":17}]}